bombastik-0.0.1.dist-info/licenses/LICENSE
src/project/__init__.py
bombastik-0.0.1.dist-info/METADATA
bombastik-0.0.1.dist-info/WHEEL
bombastik-0.0.1.dist-info/top_level.txt
bombastik-0.0.1.dist-info/RECORD
