Metadata-Version: 2.4
Name: Bombastik
Version: 0.0.1
Summary: A simple package for sports activity
Author-email: Bora Canbula <bora.canbula@cbu.edu.tr>
Project-URL: Homepage, https://github.com/linaund1000/bombastik
Keywords: ,bombastik
Classifier: Development Status :: 3 - Alpha
Classifier: Intended Audience :: Developers
Classifier: License :: OSI Approved :: MIT License
Classifier: Programming Language :: Python :: 3
Classifier: Operating System :: OS Independent
Requires-Python: >=3.6.0
License-File: LICENSE
Dynamic: license-file
